{
  "tu_khoa_phap_ly_lao_dong": {
    "chu_the_va_co_quan_to_chuc": [
      "người lao động",
      "người sử dụng lao động",
      "người làm việc không có quan hệ lao động",
      "tổ chức đại diện người lao động tại cơ sở",
      "tổ chức đại diện người sử dụng lao động",
      "công đoàn",
      "hòa giải viên lao động",
      "Hội đồng trọng tài lao động",
      "Tòa án nhân dân",
      "thanh tra lao động"
    ],
    "viec_lam_va_hop_dong_lao_dong": [
      "việc làm",
      "tuyển dụng lao động",
      "quản lý lao động",
      "quan hệ lao động",
      "hợp đồng lao động",
      "giao kết hợp đồng lao động",
      "hợp đồng lao động không xác định thời hạn",
      "hợp đồng lao động xác định thời hạn",
      "phụ lục hợp đồng lao động",
      "hợp đồng lao động vô hiệu",
      "cho thuê lại lao động",
      "thử việc",
      "chấm dứt hợp đồng lao động",
      "đơn phương chấm dứt hợp đồng lao động",
      "trợ cấp thôi việc",
      "trợ cấp mất việc làm",
      "học nghề, tập nghề",
      "hợp đồng đào tạo nghề"
    ],
    "tien_luong_va_thu_nhap": [
      "tiền lương",
      "mức lương tối thiểu",
      "thang lương, bảng lương",
      "định mức lao động",
      "trả lương",
      "tạm ứng tiền lương",
      "khấu trừ tiền lương",
      "chế độ nâng lương, nâng bậc",
      "phụ cấp",
      "trợ cấp",
      "thưởng",
      "tiền lương làm thêm giờ",
      "tiền lương làm việc vào ban đêm",
      "tiền lương ngừng việc"
    ],
    "thoi_gio_lam_viec_va_nghi_ngoi": [
      "thời giờ làm việc bình thường",
      "giờ làm việc ban đêm",
      "làm thêm giờ",
      "thời giờ nghỉ ngơi",
      "nghỉ trong giờ làm việc",
      "nghỉ chuyển ca",
      "nghỉ hằng tuần",
      "nghỉ lễ, tết",
      "nghỉ hằng năm",
      "nghỉ việc riêng",
      "nghỉ không hưởng lương"
    ],
    "ky_luat_lao_dong_va_trach_nhiem_vat_chat": [
      "kỷ luật lao động",
      "nội quy lao động",
      "xử lý kỷ luật lao động",
      "khiển trách",
      "kéo dài thời hạn nâng lương",
      "cách chức",
      "sa thải",
      "xóa kỷ luật, giảm thời hạn chấp hành kỷ luật lao động",
      "tạm đình chỉ công việc",
      "trách nhiệm vật chất",
      "bồi thường thiệt hại"
    ],
    "an_toan_ve_sinh_lao_dong_va_bao_hiem": [
      "an toàn, vệ sinh lao động",
      "tai nạn lao động",
      "bệnh nghề nghiệp",
      "bảo hiểm xã hội",
      "bảo hiểm y tế",
      "bảo hiểm thất nghiệp",
      "tuổi nghỉ hưu"
    ],
    "lao_dong_dac_thu": [
      "lao động nữ",
      "bảo vệ thai sản",
      "nghỉ thai sản",
      "lao động chưa thành niên",
      "người lao động cao tuổi",
      "người lao động Việt Nam đi làm việc ở nước ngoài",
      "người lao động nước ngoài làm việc tại Việt Nam",
      "giấy phép lao động",
      "người lao động là người khuyết tật",
      "người lao động làm giúp việc gia đình"
    ],
    "doi_thoai_thuong_luong_va_tranh_chap": [
      "đối thoại tại nơi làm việc",
      "thương lượng tập thể",
      "thỏa ước lao động tập thể",
      "tranh chấp lao động",
      "tranh chấp lao động cá nhân",
      "tranh chấp lao động tập thể",
      "đình công"
    ],
    "hanh_vi_bi_cam": [
      "cưỡng bức lao động",
      "phân biệt đối xử trong lao động",
      "quấy rối tình dục tại nơi làm việc"
    ]
  }
}
